airflow/providers/microsoft/msgraph/__init__.py
airflow/providers/microsoft/msgraph/hooks/evaluator.py
airflow/providers/microsoft/msgraph/hooks/msgraph.py
airflow/providers/microsoft/msgraph/operators/msgraph.py
airflow/providers/microsoft/msgraph/triggers/msgraph.py
airflow/providers/microsoft/msgraph/triggers/serializer.py
airflow/providers/microsoft/msgraph/version.py
apache_airflow_providers_msgraph-1.0.1.dist-info/METADATA
apache_airflow_providers_msgraph-1.0.1.dist-info/WHEEL
apache_airflow_providers_msgraph-1.0.1.dist-info/entry_points.txt
apache_airflow_providers_msgraph-1.0.1.dist-info/RECORD
