Metadata-Version: 2.1
Name: apache-airflow-providers-msgraph
Version: 1.0.1
Summary: Airflow provider package for Microsoft Graph API
License: Proprietary
Author: David Blain
Author-email: david.blain@infrabel.be
Requires-Python: >=3.8.1,<4
Classifier: License :: Other/Proprietary License
Classifier: Programming Language :: Python :: 3
Classifier: Programming Language :: Python :: 3.9
Classifier: Programming Language :: Python :: 3.10
Classifier: Programming Language :: Python :: 3.11
Classifier: Programming Language :: Python :: 3.12
Requires-Dist: aiostream (>=0.5.2,<0.6.0)
Requires-Dist: apache-airflow (>2.7)
Requires-Dist: msgraph-beta-sdk (>=1.0.0,<2.0.0)
Requires-Dist: msgraph-sdk (>=1.0.0,<2.0.0)
